[
    {
        "id": 0,
        "title": "PSG vs Las Brujas",
        "league": "Champions League",
        "date": "24/02/2022",
        "logo": "champions"
    },
    {
        "id": 1,
        "title": "Tottenham vs Chelsea",
        "league": "Premier League",
        "date": "30/03/2022",
        "logo": "premier"
    },
    {
        "id": 2,
        "title": "Man. United vs West Ham",
        "league": "Premier League",
        "date": "25/12/2022",
        "logo": "premier"
    },
    {
        "id": 3,
        "title": "Millonarios vs Huila",
        "league": "Bet Play",
        "date": "24/02/2021",
        "logo": "betplay"
    },
    {
        "id": 4,
        "title": "Santa Fe vd Cali",
        "league": "Bet Play",
        "date": "07/06/2023",
        "logo": "betplay"
    },
    {
        "id": 5,
        "title": "Man. United vs Young Boys",
        "league": "Champions League",
        "date": "24/02/2022",
        "logo": "champions"
    },
    {
        "id": 6,
        "title": "Barcelona vs Bayern Mun.",
        "league": "Champions League",
        "date": "24/02/2022",
        "logo": "champions"
    }
]
